graph_wrap/__init__.py
graph_wrap/graphql_transformer.py
graph_wrap/django_rest_framework/__init__.py
graph_wrap/django_rest_framework/api_transformer.py
graph_wrap/django_rest_framework/graphql_view.py
graph_wrap/django_rest_framework/query_resolver.py
graph_wrap/django_rest_framework/schema_factory.py
graph_wrap/shared/__init__.py
graph_wrap/shared/query_resolver.py
graph_wrap/shared/schema_factory.py
graph_wrap/tastypie/__init__.py
graph_wrap/tastypie/api_transformer.py
graph_wrap/tastypie/graphql_resource.py
graph_wrap/tastypie/graphql_view.py
graph_wrap/tastypie/query_resolver.py
graph_wrap/tastypie/schema_factory.py
tests/__init__.py
tests/apps.py
tests/manage.py
tests/models.py
tests/settings.py
tests/urls.py
tests/django_rest_framework_api/__init__.py
tests/django_rest_framework_api/api.py
tests/django_rest_framework_api/test_api.py
tests/django_rest_framework_api/urls.py
tests/tastypie_api/__init__.py
tests/tastypie_api/api.py
tests/tastypie_api/test_api.py
tests/tastypie_api/urls.py
graph_wrap-0.1.3.dist-info/LICENSE
graph_wrap-0.1.3.dist-info/METADATA
graph_wrap-0.1.3.dist-info/WHEEL
graph_wrap-0.1.3.dist-info/top_level.txt
graph_wrap-0.1.3.dist-info/RECORD
