Metadata-Version: 2.1
Name: graph-wrap
Version: 0.1.3
Summary: Extend an existing Django REST Framework or Tastypie API with a GraphQL interface with a only a couple of lines of code.
Home-page: https://github.com/PaulGilmartin/graph_wrap
Author: Paul Gilmartin
Author-email: paul.gilmartin89@gmail.com
Project-URL: Source, https://github.com/PaulGilmartin/graph_wrap
Keywords: tastypie graphene django graphql rest api djangorestframework drf
Classifier: Development Status :: 3 - Alpha
Classifier: Intended Audience :: Developers
Classifier: Topic :: Software Development :: Build Tools
Classifier: License :: OSI Approved :: MIT License
Classifier: Programming Language :: Python :: 2.7
Classifier: Programming Language :: Python :: 3
Classifier: Programming Language :: Python :: 3.5
Classifier: Programming Language :: Python :: 3.6
Classifier: Programming Language :: Python :: 3.7
Requires-Python: >=3.6,  <4
License-File: LICENSE
Requires-Dist: graphene-django
